xmp/__init__.py
xmp_tool-0.9.2.dist-info/DESCRIPTION.rst
xmp_tool-0.9.2.dist-info/entry_points.txt
xmp_tool-0.9.2.dist-info/METADATA
xmp_tool-0.9.2.dist-info/metadata.json
xmp_tool-0.9.2.dist-info/RECORD
xmp_tool-0.9.2.dist-info/top_level.txt
xmp_tool-0.9.2.dist-info/WHEEL
