Metadata-Version: 2.0
Name: xmp-tool
Version: 0.9.2
Summary: CLI utility to read/write XMP fields in files
Home-page: https://github.com/gaqzi/py-xmp-tool
Author: Björn Andersson
Author-email: ba@sanitarium.se
License: BSD License
Platform: UNKNOWN
Classifier: Environment :: Console
Classifier: License :: OSI Approved :: BSD License
Classifier: Programming Language :: Python
Classifier: Topic :: Utilities
Classifier: Programming Language :: Python :: 2
Classifier: Programming Language :: Python :: 2.6
Classifier: Programming Language :: Python :: 2.7
Classifier: Programming Language :: Python :: 3
Classifier: Programming Language :: Python :: 3.4
Requires-Dist: python-xmp-toolkit (>=2.0.1)
